zeit/deploynotify/__init__.py
zeit/deploynotify/__main__.py
zeit/deploynotify/base.py
zeit/deploynotify/changelog.py
zeit/deploynotify/cli.py
zeit/deploynotify/github.py
zeit/deploynotify/grafana.py
zeit/deploynotify/honeycomb.py
zeit/deploynotify/jira.py
zeit/deploynotify/slack.py
zeit/deploynotify/speedcurve.py
zeit/deploynotify/tests/__init__.py
zeit/deploynotify/tests/test_changelog.py
zeit/deploynotify/tests/test_cli.py
zeit_deploynotify-1.13.0.dist-info/METADATA
zeit_deploynotify-1.13.0.dist-info/WHEEL
zeit_deploynotify-1.13.0.dist-info/RECORD
