Metadata-Version: 2.4
Name: zeit.deploynotify
Version: 1.13.0
Project-URL: Repository, https://github.com/ZeitOnline/deployment-notify
Author-email: Zeit Online <zon-backend@zeit.de>
Requires-Dist: click
Requires-Dist: jira
Requires-Dist: requests
